chain_nhem_nhem/__init__.py
chain_nhem_nhem/config.py
chain_nhem_nhem/logging.py
chain_nhem_nhem/agent/__init__.py
chain_nhem_nhem/agent/agent.py
chain_nhem_nhem/agent/factory.py
chain_nhem_nhem/agent/models.py
chain_nhem_nhem/core/__init__.py
chain_nhem_nhem/core/messages.py
chain_nhem_nhem/helpers/gemini_helper.py
chain_nhem_nhem/llm/__init__.py
chain_nhem_nhem/llm/factory.py
chain_nhem_nhem/llm/llm_driver.py
chain_nhem_nhem/llm/registry.py
chain_nhem_nhem/llm/drivers/__init__.py
chain_nhem_nhem/llm/drivers/gemini_driver.py
chain_nhem_nhem/tools/__init__.py
chain_nhem_nhem/tools/base.py
chain_nhem_nhem/tools/registry.py
chain_nhem_nhem/tools/weather_tool.py
chain_nhem_nhem-0.1.0.dist-info/licenses/LICENSE
chain_nhem_nhem-0.1.0.dist-info/METADATA
chain_nhem_nhem-0.1.0.dist-info/WHEEL
chain_nhem_nhem-0.1.0.dist-info/top_level.txt
chain_nhem_nhem-0.1.0.dist-info/RECORD
