Metadata-Version: 2.4
Name: chain-nhem-nhem
Version: 0.1.0
Summary: A minimal agent framework
Author-email: Ewerton Azevedo <ewertonzvd@gmail.com>
License: MIT License
Project-URL: Homepage, https://github.com/EwertonZ/chain-nhem-nhem
Project-URL: Repository, https://github.com/EwertonZ/chain-nhem-nhem
Project-URL: Issues, https://github.com/EwertonZ/chain-nhem-nhem/issues
Requires-Python: >=3.10
License-File: LICENSE
Requires-Dist: pydantic
Requires-Dist: python-dotenv
Requires-Dist: google-generativeai
Dynamic: license-file
